iinfer/__init__.py
iinfer/__main__.py
iinfer/autoload.py
iinfer/logconf_iinfer.yml
iinfer/version.py
iinfer/app/__init__.py
iinfer/app/app.py
iinfer/app/client.py
iinfer/app/common.py
iinfer/app/injection.py
iinfer/app/install.py
iinfer/app/postprocess.py
iinfer/app/predict.py
iinfer/app/redis.py
iinfer/app/train.py
iinfer/app/web.py
iinfer/app/commons/module.py
iinfer/app/features/cli/__init__.py
iinfer/app/features/cli/iinfer_client_capture.py
iinfer/app/features/cli/iinfer_client_deploy.py
iinfer/app/features/cli/iinfer_client_deploy_list.py
iinfer/app/features/cli/iinfer_client_predict.py
iinfer/app/features/cli/iinfer_client_predict_type_list.py
iinfer/app/features/cli/iinfer_client_read_dir.py
iinfer/app/features/cli/iinfer_client_start.py
iinfer/app/features/cli/iinfer_client_stop.py
iinfer/app/features/cli/iinfer_client_train.py
iinfer/app/features/cli/iinfer_client_train_type_list.py
iinfer/app/features/cli/iinfer_client_undeploy.py
iinfer/app/features/cli/iinfer_gui_start.py
iinfer/app/features/cli/iinfer_install_insightface.py
iinfer/app/features/cli/iinfer_install_mmcls.py
iinfer/app/features/cli/iinfer_install_mmdet.py
iinfer/app/features/cli/iinfer_install_mmpretrain.py
iinfer/app/features/cli/iinfer_install_mmseg.py
iinfer/app/features/cli/iinfer_install_onnx.py
iinfer/app/features/cli/iinfer_install_redis.py
iinfer/app/features/cli/iinfer_install_server.py
iinfer/app/features/cli/iinfer_postprocess_cls_judge.py
iinfer/app/features/cli/iinfer_postprocess_cmd.py
iinfer/app/features/cli/iinfer_postprocess_csv.py
iinfer/app/features/cli/iinfer_postprocess_det_clip.py
iinfer/app/features/cli/iinfer_postprocess_det_face_store.py
iinfer/app/features/cli/iinfer_postprocess_det_filter.py
iinfer/app/features/cli/iinfer_postprocess_det_judge.py
iinfer/app/features/cli/iinfer_postprocess_httpreq.py
iinfer/app/features/cli/iinfer_postprocess_seg_bbox.py
iinfer/app/features/cli/iinfer_postprocess_seg_filter.py
iinfer/app/features/cli/iinfer_postprocess_showimg.py
iinfer-0.12.3.dist-info/licenses/LICENSE
iinfer-0.12.3.dist-info/METADATA
iinfer-0.12.3.dist-info/WHEEL
iinfer-0.12.3.dist-info/entry_points.txt
iinfer-0.12.3.dist-info/top_level.txt
iinfer-0.12.3.dist-info/RECORD
