Metadata-Version: 2.4
Name: iinfer
Version: 0.12.3
Summary: iinfer: An application that executes AI model files in onnx or mmlab format.
Author-email: hamacom2004jp <hamacom2004jp@gmail.com>
License: MIT
Project-URL: Homepage, https://github.com/hamacom2004jp/iinfer
Project-URL: Documentation, https://hamacom2004jp.github.io/iinfer/index.html
Project-URL: Repository, https://github.com/hamacom2004jp/iinfer
Keywords: mmdetection,mmsegmentation,onnxruntime,inference,image,ai,model,audit,cli,excel,fastapi,mcp,redis,restapi,web
Classifier: Development Status :: 4 - Beta
Classifier: Intended Audience :: Developers
Classifier: Intended Audience :: Information Technology
Classifier: Intended Audience :: System Administrators
Classifier: License :: OSI Approved :: MIT License
Classifier: Natural Language :: Japanese
Classifier: Programming Language :: Python
Classifier: Topic :: Utilities
Requires-Python: >=3.8
License-File: LICENSE
Requires-Dist: cmdbox<0.7.4,>=0.7.3
Requires-Dist: motpy
Requires-Dist: opencv-python
Requires-Dist: urllib3
Provides-Extra: agent
Requires-Dist: pydantic<3.0.0,>=2.0.0; extra == "agent"
Requires-Dist: fastmcp>=2.14.0; extra == "agent"
Requires-Dist: mcp<2.0.0,>=1.10.0; extra == "agent"
Requires-Dist: google-adk>=1.21.0; extra == "agent"
Requires-Dist: litellm; extra == "agent"
Provides-Extra: saml
Requires-Dist: python3-saml; extra == "saml"
Requires-Dist: xmlsec==1.3.13; extra == "saml"
Dynamic: license-file
